deadline_worker_agent/__init__.py
deadline_worker_agent/__main__.py
deadline_worker_agent/_version.py
deadline_worker_agent/api_models.py
deadline_worker_agent/capabilities.py
deadline_worker_agent/errors.py
deadline_worker_agent/feature_flag.py
deadline_worker_agent/file_system_operations.py
deadline_worker_agent/log_messages.py
deadline_worker_agent/metrics.py
deadline_worker_agent/progress.py
deadline_worker_agent/session_events.py
deadline_worker_agent/utils.py
deadline_worker_agent/worker.py
deadline_worker_agent/aws/__init__.py
deadline_worker_agent/aws/deadline/__init__.py
deadline_worker_agent/aws_credentials/__init__.py
deadline_worker_agent/aws_credentials/aws_configs.py
deadline_worker_agent/aws_credentials/boto3_sessions.py
deadline_worker_agent/aws_credentials/credentials_refresher.py
deadline_worker_agent/aws_credentials/queue_boto3_session.py
deadline_worker_agent/aws_credentials/temporary_credentials.py
deadline_worker_agent/aws_credentials/worker_boto3_session.py
deadline_worker_agent/boto/__init__.py
deadline_worker_agent/boto/config.py
deadline_worker_agent/boto/logger.py
deadline_worker_agent/boto/retries.py
deadline_worker_agent/boto/shim.py
deadline_worker_agent/config/__init__.py
deadline_worker_agent/config/__main__.py
deadline_worker_agent/config/cli_args.py
deadline_worker_agent/config/config.py
deadline_worker_agent/config/config_file.py
deadline_worker_agent/config/errors.py
deadline_worker_agent/config/settings.py
deadline_worker_agent/config/toml_comment.py
deadline_worker_agent/installer/__init__.py
deadline_worker_agent/installer/install.sh
deadline_worker_agent/installer/win_installer.py
deadline_worker_agent/installer/worker.toml.example
deadline_worker_agent/linux/__init__.py
deadline_worker_agent/linux/capabilities.py
deadline_worker_agent/log_sync/__init__.py
deadline_worker_agent/log_sync/cloudwatch.py
deadline_worker_agent/log_sync/loggers.py
deadline_worker_agent/scheduler/__init__.py
deadline_worker_agent/scheduler/log.py
deadline_cloud_worker_agent-0.28.21.dist-info/METADATA
deadline_cloud_worker_agent-0.28.21.dist-info/WHEEL
deadline_cloud_worker_agent-0.28.21.dist-info/entry_points.txt
deadline_cloud_worker_agent-0.28.21.dist-info/licenses/LICENSE
deadline_cloud_worker_agent-0.28.21.dist-info/licenses/NOTICE
deadline_cloud_worker_agent-0.28.21.dist-info/RECORD
