Metadata-Version: 2.4
Name: deadline-cloud-worker-agent
Version: 0.28.21
Summary: The AWS Deadline Cloud worker agent can be used to run a worker in an AWS Deadline Cloud fleet
Project-URL: Homepage, https://github.com/aws-deadline/deadline-cloud-worker-agent
Project-URL: Source, https://github.com/aws-deadline/deadline-cloud-worker-agent
Author: Amazon Web Services
License-Expression: Apache-2.0
License-File: LICENSE
License-File: NOTICE
Classifier: Development Status :: 5 - Production/Stable
Classifier: Intended Audience :: End Users/Desktop
Classifier: License :: OSI Approved :: Apache Software License
Classifier: Operating System :: Microsoft :: Windows
Classifier: Operating System :: POSIX :: Linux
Classifier: Programming Language :: Python
Classifier: Programming Language :: Python :: 3 :: Only
Classifier: Programming Language :: Python :: 3.9
Classifier: Programming Language :: Python :: 3.10
Classifier: Programming Language :: Python :: 3.11
Classifier: Programming Language :: Python :: 3.12
Classifier: Programming Language :: Python :: 3.13
Requires-Python: >=3.9
Requires-Dist: boto3>=1.34.75
Requires-Dist: deadline<0.55,>=0.54.0
Requires-Dist: openjd-model<0.9,>=0.8.1
Requires-Dist: openjd-sessions==0.10.6
Requires-Dist: psutil<8.0,>=5.9
Requires-Dist: pydantic<3,>=2.10
Requires-Dist: pywin32==310; platform_system == 'Windows'
Requires-Dist: requests==2.32.*
Requires-Dist: requests~=2.31
Requires-Dist: tomli==2.0.*; python_version < '3.11'
Requires-Dist: tomlkit<0.15,>=0.13
Requires-Dist: typing-extensions~=4.8
